sean/__init__.py
sean/handlers.py
sean/sean.py
sean/seantype.py
sean-0.8.0.2.dist-info/DESCRIPTION.rst
sean-0.8.0.2.dist-info/METADATA
sean-0.8.0.2.dist-info/RECORD
sean-0.8.0.2.dist-info/WHEEL
sean-0.8.0.2.dist-info/metadata.json
sean-0.8.0.2.dist-info/top_level.txt
